klsosdoids2/init.py
klsosdoids2/main.py
klsosdoids2-0.1.dist-info/METADATA
klsosdoids2-0.1.dist-info/WHEEL
klsosdoids2-0.1.dist-info/entry_points.txt
klsosdoids2-0.1.dist-info/top_level.txt
klsosdoids2-0.1.dist-info/RECORD
