Metadata-Version: 2.4
Name: klsosdoids2
Version: 0.1
Requires-Dist: requests
Dynamic: requires-dist
